odoo/addons/sale_report_crossed_out_original_price/README.rst
odoo/addons/sale_report_crossed_out_original_price/__manifest__.py
odoo/addons/sale_report_crossed_out_original_price/readme/CONFIGURE.rst
odoo/addons/sale_report_crossed_out_original_price/readme/CONTRIBUTORS.rst
odoo/addons/sale_report_crossed_out_original_price/readme/DESCRIPTION.rst
odoo/addons/sale_report_crossed_out_original_price/readme/INSTALL.rst
odoo/addons/sale_report_crossed_out_original_price/readme/USAGE.rst
odoo/addons/sale_report_crossed_out_original_price/reports/report_saleorder_document.xml
odoo/addons/sale_report_crossed_out_original_price/static/description/icon.png
odoo/addons/sale_report_crossed_out_original_price/static/description/index.html
odoo/addons/sale_report_crossed_out_original_price/static/img/example.png
odoo14_addon_sale_report_crossed_out_original_price-14.0.1.1.0.dist-info/METADATA
odoo14_addon_sale_report_crossed_out_original_price-14.0.1.1.0.dist-info/WHEEL
odoo14_addon_sale_report_crossed_out_original_price-14.0.1.1.0.dist-info/top_level.txt
odoo14_addon_sale_report_crossed_out_original_price-14.0.1.1.0.dist-info/RECORD
