Metadata-Version: 2.1
Name: odoo14-addon-sale-report-crossed-out-original-price
Version: 14.0.1.1.0
Summary: Sale report crossed out original price when a discount exists
Home-page: https://github.com/OCA/sale-reporting
Author: Sygel, Odoo Community Association (OCA)
Author-email: support@odoo-community.org
License: AGPL-3
Platform: UNKNOWN
Classifier: Programming Language :: Python
Classifier: Framework :: Odoo
Classifier: Framework :: Odoo :: 14.0
Classifier: License :: OSI Approved :: GNU Affero General Public License v3
Requires-Python: >=3.6
Requires-Dist: odoo (<14.1dev,>=14.0a)
